Workbook

Sheet Introduction
A1: Analyse de risque EBIOS RM : Classeur de travail
A4: Projet 07 : UniCampus+ | Cours 4CS08 - Analyse de risques | Méthode EBIOS Risk Manager
A6: 1. Composition du groupe
A7: Virgile Thonnier Timoté Lacambra Jeremy Giudicelli Ghislain Maugenest
A9: 2. Méthode utilisée pour la réalisation de l'analyse de risque : les 5 ateliers EBIOS RM
A10: Atelier | B10: Intitulé | C10: Objet | D10: Sortie(s) principale(s)
A11: A1 | B11: Portée et référentiel de sécurité | C11: Définir le périmètre, les missions, les valeurs métier, les biens supports, les événements redoutés (ER) et leur gravité | D11: Portée opérationnelle et techniques ER et niveaux de gravité
A12: A2 | B12: Origines des risques | C12: Identifier les couples Source de risque / Objectif visé (SR/OV) et leur pertinence. | D12: Couples SR/OV retenus Couples SR/OV surveillés Liens SR/OV - ER
A13: A3 | B13: Scénarios stratégiques | C13: Identification des parties prenantes clés de l'écosystème et élaboration de scénarios de risque de haut niveau | D13: Cartographie des menaces pesant sur l'écosystème Scénarios stratégiques Mesures de sécurité mises en place pour l'écosystème
A14: A4 | B14: Scénarios opérationnels | C14: Élaborer des scénarios opérationnels décrivant les procédures techniques qui seront mises en œuvre par les sources de risque | D14: Scénarios opérationnels Évaluation de la probabilité des scénarios opérationnels
A15: A5 | B15: Traitement du risque | C15: Placer les risques sur la matrice gravité × vraisemblance, décider du traitement, planifier les mesures. | D15: Plan de traitement Risque résiduel
A17: 3. Plan du classeur
A18: Onglet | B18: Atelier | C18: Contenu | D18: État
A19: Introduction | B19: A0 | C19: Méthodologie, conventions, plan du classeur | D19: Rempli
A20: A1.0 Périmètre | B20: A1 | C20: Cadre de l'étude, périmètres métier et technique, participants | D20: Rempli
A21: A1.1 Missions & VM | B21: A1 | C21: Missions, valeurs métier (nature, description) | D21: Rempli
A22: A1.2 Biens supports | B22: A1 | C22: Biens supports par VM (valeurs métier), descriptions, responsables | D22: Rempli
A23: A1.3 Échelle de gravité | B23: A1 | C23: Échelle et critères de classification de gravité calibrée pour Unicampus (G1 à G4) | D23: Rempli
A24: A1.4 Événements redoutés | B24: A1 | C24: ER rattachés aux VM, cotation sur l'échelle | D24: Rempli
A25: A2.0 Échelle de pertinence | B25: A2 | C25: Matrice de pertinence des couples SR/OV | D25: Rempli
A26: A2.1 Sources de risque | B26: A2 | C26: Typologie des 5 sources de risque retenues avec profils | D26: Rempli
A27: A2.2 Couples SR-OV | B27: A2 | C27: Couples évalués (motivation, ressources, pertinence calculée, décision) | D27: Rempli
A28: A2.3 Liens couples - ER | B28: A2 | C28: Synthèse rapprochant les ER de A1.4 et les couples SR/OV | D28: Rempli
A29: A3.0 Critères de dangerosité | B29: A3 | C29: Echelle pour l'analyse du risque induit par les parties prenantes (PP) avec les critères de pénétration, dépendance, maturité et confiance | D29: Rempli
... A42: A5.5 Cadre de suivi | B42: A5 | C42: Indicateurs, comités, déclencheurs de mise à jour | D42: Rempli

Sheet A1.0 Périmètre
A1: A1.0 - Cadre et périmètre de l'étude
A4: Sortie attendue de la partie cadrage de l'atelier 1 : description du périmètre métier et technique, et liste des participants (réels ou cibles) de l'analyse de risque.
A6: Éléments de cadrage
B7: Élément | C7: Description
A8: 1 | B8: Objet d'étude | C8: Système d'information de l'université UniCampus+ tel que présenté dans le fichier Projet_07_UniCampus.md et modélisé par la maquette déployé sur OpenStack : Établissement public d'enseignement supérieur accueillant 12 000 étudiants et 500 personnels (enseignants, administratifs, chercheurs, techniciens), réparti sur plusieurs bâtiments.
A9: 2 | B9: Périmètre métier | C9: Les trois missions principales de l'organisme que nous couvrons dans cette analyse de risques sont : • M1 - Enseignement : formation initiale des 12 000 étudiants ; • M2 - Recherche : production scientifique des laboratoires ; • M3 - Administration : RH, scolarité administrative, finances.
A10: 3 | B10: Périmètre technique | C10: Périmètre technique modélisé dans la maquette v1 (état de la maquette au moment de la réalisation de l'analyse; nous serons éventuellement ammené à reduire le nombre de machines virtuelles et donc à condenser les biens support sur certaines machines) : 11 machines virtuelles sur un seul subnet (192.168.107.0/24) 1 firewall périmétrique (`uc-fw-legacy`) 1 VPN d'accès distant (`uc-vpn-legacy`) 5 serveurs applicatifs (Moodle, mail, LDAP, RH, recherche) 1 base de données back-end RH (`uc-db-rh`) 3 postes clients (étudiant, enseignant, DSI)
A11: 4 | B11: Participants à l'analyse (cibles en organisation réelle) | C11: • Équipes métier : direction des études, direction de la recherche, DRH ; • RSSI de l'établissement ; • DSI : architecte réseau, administrateur systèmes, responsable IAM ; • Équipe de gestion documentaire (DPO). Dans le cadre du projet 4CS08, l'analyse est portée par le groupe projet jouant l'ensemble de ces rôles.
A12: 5 | B12: Cadre normatif et référentiels mobilisés | C12: • Méthode EBIOS Risk Manager 2018 (ANSSI) ; • Guide d'hygiène informatique ANSSI (11 règles citées dans la fiche projet : R4, R7, R8, R9, R10, R13, R22, R25, R31, R35, R40) ; • Référentiel RGPD pour les données personnelles (étudiants et personnels) ; • ISO/IEC 27005 pour le processus général de gestion des risques. (indiqué à titre indicatif dans le cadre d'une éventuelle réutilsation de ce fichier pour d'autres analyses de risques)

Sheet A1.1 Missions & VM
A1: A1.1 - Missions et valeurs métier
A4: Sortie attendue de la partie cadrage de l'atelier 1 : Pour chaque mission de l'objet d'étude, lister les valeurs métier (VM) qui la portent. Nature : Processus (activité) ou Information (donnée). Une VM peut être de nature mixte. Convention de codification : Mx pour les missions, VMx.y pour les valeurs métier (x = numéro de mission).
A6: Tableau des missions et valeurs métier
A7: Code mission | B7: Mission | C7: Valeur métier | D7: Nature | E7: Description
A8: M1 | B8: Enseignement Assurer la formation des 12000 étudiants | C8: VM1.1 : Diffusion des contenus pédagogiques | D8: Processus | E8: Activité de mise à disposition des cours, supports, devoirs, exercices, corrigés et ressources documentaires aux étudiants, organisée par UE et par promotion, avec dépôt des productions étudiantes (devoirs, examens écrits).
C9: VM1.2 : Évaluation et notation | D9: Processus | E9: Activité de notation des productions étudiantes, calcul des moyennes, gestion des sessions d'examens et des jurys.
C10: VM1.3 : Résultats académiques | D10: Information | E10: Notes individuelles, moyennes, validations d'UE, attestations, diplômes : informations à très forte exigence d'intégrité et d'authenticité.
C11: VM1.4 : Communication pédagogique | D11: Processus | E11: Échanges quotidiens entre enseignants, étudiants et services de scolarité via messagerie et listes de diffusion (annonces, convocations, conventions).
C12: VM1.5 : Accès aux ressources documentaires | D12: Processus | E12: Accès des étudiants, enseignants et chercheurs à la bibliothèque numérique : bases bibliographiques, revues scientifiques, ouvrages en ligne, archives ouvertes. Non mis en place dans la maquette v1 et déclarée pour complétude du périmètre métier et car il est mentionné dans la fiche de description du projet. On peut considèrer que ce processus est géré par un prestataire donc analysé dans le cadre de l'analyse des parties prenantes
A13: M2 | B13: Recherche Produire, partager et diffuser de la connaissance scientifique au sein des laboratoires, en collaboration avec des partenaires académiques et industriels. | C13: VM2.1 : Conduite des activités de recherche | D13: Processus | E13: Activité scientifique réalisée par les enseignants-chercheurs et chercheurs : conception d'expériences, calcul scientifique (notebooks, simulations), traitement et analyse de données.
C14: VM2.2 : Patrimoine scientifique | D14: Information | E14: Données expérimentales brutes et traitées, codes et notebooks, articles en cours de rédaction, résultats préliminaires non publiés, antériorités brevetables. Confidentialité critique.
C15: VM2.3 : Collaboration et diffusion scientifique | D15: Processus | E15: Échanges avec partenaires académiques (laboratoires associés) et industriels (financements, contrats de recherche), publications, dépôts de brevets, communications scientifiques.
A16: M3 | B16: Administration Gérer les ressources humaines (paie, contrats), la scolarité administrative et les fonctions financières de l'établissement. | C16: VM3.1 : Gestion des ressources humaines | D16: Processus | E16: Activité administrative comprenant : production de la paie mensuelle, gestion des contrats de travail, suivi des carrières, gestion des absences et congés, tenue des dossiers individuels du personnel.
C17: VM3.2 : Données personnelles et contractuelles | D17: Information | E17: Données personnelles (identité, NIR, RIB, adresse, situation familiale) et contractuelles (salaire, grade, ancienneté) des 500 personnels. Données soumises au RGPD avec base légale d'exécution du contrat de travail.
C18: VM3.3 : Gestion administrative des étudiants (scolarité) | D18: Processus | E18: Inscriptions administratives, gestion des conventions de stage, des bourses, des certificats de scolarité, des transferts de dossier.
C19: VM3.4 : Gestion financière et comptable | D19: Processus | E19: Comptabilité générale, traitement des dépenses et recettes, gestion des marchés publics, relations avec l'agent comptable.

Sheet A1.2 Biens supports
A1: A1.2 - Biens supports
A4: Sortie attendue de la partie cadrage de l'atelier 1 : Pour chaque valeur métier, identifier les biens supports (systèmes, applications, réseaux, postes, locaux, contrats…) qui la portent. Un même bien support peut servir plusieurs VM (nous le qualifions alors de "transverse" dans le document). Le responsable est l'entité ou la personne (interne ou externe) en charge de l'exploitation du bien. Les descriptions des biens supports correspondent à ce que notre groupe avait engisagé pour la maquette lors de la réalisation de l'analyse de risque. Nous notons aussi que (comme dans l'exemple du cours) les biens supports de type informationnels (par exemple, contrat) sont représentés dans cette analyse de risques par le(s) bien(s) support(s) qui les stockent.
A6: Tableau des biens supports
A7: Code BS | B7: Dénomination | C7: Description | D7: VM associée(s) | E7: Responsable | F7: Interne / Externe
A8: BS01 | B8: Plateforme Moodle (`uc-srv-moodle`) | C8: Serveur applicatif Apache + PHP avec base MariaDB locale (instance liée à 127.0.0.1), hébergeant les espaces de cours, le dépôt de devoirs, les modules d'évaluation. Exposé en façade Internet via HTTP. | D8: VM1.1, VM1.2 | E8: DSI | F8: Interne
A9: BS02 | B9: Base de données Moodle (intégrée à `uc-srv-moodle`) | C9: Instance `mariadb-server` locale stockant les comptes utilisateurs (table `mdl_user`, hash bcrypt) et les notes (tables `mdl_grade_*`). Bind sur la boucle locale uniquement. | D9: VM1.3 | E9: DSI | F9: Interne
A10: BS03 | B10: Serveur de messagerie (`uc-srv-mail`) | C10: Postfix (SMTP/25), Dovecot (IMAP/143, POP3/110), comptes Unix locaux + Dovecot, hash crypt. Exposé en façade Internet pour SMTP et IMAP. | D10: VM1.4, VM2.3, VM3.1 (transverse) | E10: DSI | F10: Interne
A11: BS04 | B11: Annuaire d'identité LDAP (`uc-srv-ldap`) | C11: OpenLDAP (slapd), suffix `dc=unicampus,dc=local`, OUs `people` et `groups`. Référentiel des comptes étudiants, enseignants, chercheurs, administratifs et DSI. Bind anonyme autorisé, TLS non configuré. | D11: Transverse (M1, M2, M3) | E11: DSI | F11: Interne
A12: BS05 | B12: Serveur de calcul et stockage de recherche (`uc-calc-recherche`) | C12: Cumule : NFS (port 2049 + rpcbind 111) et Samba (445, 139) pour le partage de fichiers scientifiques, Jupyter (8888) pour les notebooks, PostgreSQL local (127.0.0.1:5432) pour les bases scientifiques. | D12: VM2.1, VM2.2 | E12: DSI + Laboratoires | F12: Interne
A13: BS06 | B13: Application web RH (`uc-web-rh`) | C13: Application Apache + PHP exposant l'interface de gestion RH, communiquant avec `uc-db-rh` sur le port 3306. Pas d'exposition Internet directe : accessible uniquement depuis le réseau interne. | D13: VM3.1 | E13: DSI | F13: Interne
A14: BS07 | B14: Base de données RH (`uc-db-rh`) | C14: Instance MariaDB stockant les comptes (hash SHA1, sans politique de mot de passe) et les données RH des 500 personnels. Écoute sur toutes les interfaces (`0.0.0.0:3306`). | D14: VM3.2 | E14: DSI | F14: Interne
A15: BS08 | B15: Poste étudiant (`uc-poste-etu`) | C15: Poste de salle informatique (Kali Linux dans la maquette pour démonstration). Connecté en DHCP sur le réseau campus. | D15: VM1.1, VM1.4 | E15: DSI + utilisateur étudiant | F15: Interne
A16: BS09 | B16: Poste enseignant et enseignant-chercheur (`uc-poste-prof`) | C16: Poste de travail Ubuntu Desktop 22.04. Cumule les rôles enseignant et enseignant-chercheur (mêmes credentials Moodle et recherche) | D16: VM1.1, VM1.2, VM2.1, VM2.2, VM1.4 | E16: DSI + utilisateur enseignant | F16: Interne
A17: BS10 | B17: Poste administratif et DSI (`uc-poste-dsi`) | C17: Poste de travail Ubuntu Desktop 22.04 cumulant les rôles administration et DSI. Stocke en clair la clé SSH privée d'administration (`/home/ubuntu/.ssh/`). Fusion explicite de `uc-poste-admin` et du poste DSI dans la maquette v1. | D17: VM3.1 + administration transverse | E17: DSI + services administratifs | F17: Interne
A18: BS11 | B18: Passerelle périmétrique (`uc-fw-legacy`) | C18: Pare-feu historique Debian 10 avec iptables et `net.ipv4.ip_forward=1`. Politique INPUT/FORWARD/OUTPUT en ACCEPT, tables vidées, règle résiduelle d'écoute 8080/TCP. Floating IP exposant SSH d'administration. | D18: Transverse (M1, M2, M3) | E18: DSI | F18: Interne
... A20: BS13 | B20: Réseau campus (`uc-net-campus`) | C20: Unique sous-réseau interne : 192.168.107.0/24, gateway 192.168.107.1, DHCP 192.168.107.100–200. Aucun cloisonnement (étudiants, enseignants, serveurs, recherche partagent le même VLAN). | D20: Transverse (M1, M2, M3) | E20: DSI | F20: Interne

Sheet A1.3 Échelle de gravité
A1: A1.3 - Échelle de gravité (G1 à G4)
A4: Échelle calibrée pour UniCampus+ selon les axes de la slide 21 du cours : impact sur les missions/activités, sur les personnes et données, sur l'image et la gouvernance, financier, juridique. Cette échelle est utilisée pour réaliser le second rendu de l'atelier 1 pour coter les événements redoutés et à l'atelier 3 pour les scénarios stratégiques. Nous notons ici que certains des seuils ont été choisis à titre indicatif, sans l'expertise et le connaissance pour garantir la cohérence avec la réalité de l'éntité modélisée. Pour palier à cela, nous avons essayé de rester cohérents lors de la cotation des différents ER (quittent à ne pas respecter un des seuils stricto sensu).
A6: Échelle de gravité multi-dimensionnelle
A7: Niveau | B7: Libellé | C7: Missions / activité | D7: Personnes & données | E7: Image & gouvernance | F7: Finances | G7: Juridique
A8: G4 | B8: Critique - survie menacée | C8: Arrêt > 1 semaine d'un service vital (Moodle en période d'examens, paie) OU perte irrémédiable de données | D8: Fuite > 1 000 personnes OU données sensibles (NIR, santé, RIB) OU atteinte à l'intégrité physique | E8: Décision de fermeture par la tutelle, mise sous tutelle, démission du président | F8: > 1 M€ ou > 4 % du budget annuel | G8: Sanction CNIL majeure, plaintes pénales massives
A9: G3 | B9: Grave - mode très dégradé | C9: Indisponibilité 1 à 7 jours d'un service critique ; perte de données récupérables avec effort | D9: Fuite 100 à 1 000 personnes OU données personnelles ordinaires d'identification | E9: Couverture presse nationale, perte de confiance partenaires industriels ou ministère | F9: 100 k€ – 1 M€ | G9: Sanction CNIL significative, contentieux RH ou étudiant
A10: G2 | B10: Significative - mode dégradé | C10: Indisponibilité < 24 h, contournements possibles | D10: Fuite < 100 personnes, données non sensibles | E10: Communication interne nécessaire, plaintes localisées | F10: 10 k€ – 100 k€ | G10: Notification CNIL simple, pas de sanction prévisible
A11: G1 | B11: Mineure - pas d'impact opérationnel | C11: Incident résorbé sans perte de service utilisateur | D11: Aucune fuite ou fuite sans donnée personnelle | E11: Aucun impact externe | F11: < 10 k€ | G11: Aucun

Sheet A1.4 Événements redoutés
A1: A1.4 - Événements redoutés et niveau de gravité
A4: Seconde sortie de l'atlier 1 : Liste des événements redoutés (ER) identifiés au regard des valeurs métier listées en A1.1 et cotés sur l'échelle de gravité de A1.3. Chaque ER est formulé en termes métier (sans description technique) ; les scénarios techniques associés sont produits à l'atelier 4. Les catégories d'impact sont issues des six axes de répercussion EBIOS RM (missions, personnes, gouvernance, finances, juridique, image), enrichis ici de la catégorie « patrimoine intellectuel » pour la mission Recherche.
A6: Liste des événements redoutés
A7: Valeur métier | B7: Code ER | C7: Événement redouté | D7: Catégories d'impact | E7: Gravité
A8: M1 - VM1.2 / VM1.3 Évaluation et résultats académiques | B8: ER03 | C8: Altération frauduleuse des notes, moyennes ou diplômes | D8: • Impacts sur les missions et services de l'organisme • Impacts sur l'image et la confiance • Impacts juridiques (contestation des diplômes, contentieux étudiants) | E8: G3
A9: M1 - VM1.1 / VM1.4 Services pédagogiques numériques (plateforme et messagerie) | B9: ER04 | C9: Interruption de l'accès aux services pédagogiques pendant plus de 24 h | D9: • Impacts sur les missions et services de l'organisme • Impacts sur l'image et la confiance | E9: G3
B10: ER08 | C10: Détournement de la messagerie institutionnelle pour des campagnes externes malveillantes (phishing, spam) | D10: • Impacts sur l'image et la confiance | E10: G2
A11: M2 - VM2.2 Patrimoine scientifique | B11: ER02 | C11: Fuite des données et résultats de recherche de l'établissement | D11: • Impacts sur le patrimoine intellectuel • Impacts financiers (brevets compromis, contrats partenaires rompus) • Impacts sur l'image et la confiance (partenaires académiques et industriels) | E11: G3
B12: ER09 | C12: Perte ou destruction définitive des données et résultats de recherche | D12: • Impacts sur les missions et services de l'organisme • Impacts sur le patrimoine intellectuel • Impacts financiers (engagements ANR / européens compromis) | E12: G3
A13: M3 - VM3.2 Données personnelles et contractuelles | B13: ER01 | C13: Fuite massive des données personnelles des étudiants et personnels (identité, NIR, RIB, dossiers, notes) | D13: • Impacts sur les personnes (atteinte à la vie privée) • Impacts juridiques (sanction RGPD / CNIL, notification 72 h) • Impacts sur l'image et la confiance • Impacts financiers (sanction administrative, indemnisations) | E13: G4
A14: M3 - VM3.1 Gestion des ressources humaines | B14: ER05 | C14: Altération frauduleuse de la paie et des données de gestion RH | D14: • Impacts sur les missions et services de l'organisme • Impacts financiers (paie détournée ou erronée) • Impacts juridiques (contentieux RH) • Impacts sur les personnes (retard ou perte de rémunération) | E14: G3
A15: Transverse Valeurs métier de M1, M2 et M3 | B15: ER06 | C15: Interruption massive et simultanée de l'ensemble des services numériques de l'établissement | D15: • Impacts sur les missions et services de l'organisme • Impacts financiers (coût de remédiation, perte d'exploitation) • Impacts sur l'image et la confiance • Impacts juridiques (selon les données affectées) | E15: G4
A17: Note : la gravité de ER04 est calibrée à G3 hors période d'examens et G4 pendant une session d'examens

Sheet A2.0 Échelle de pertinence
A1: A2.0 - Échelle de pertinence des couples SR/OV
A4: Matrice utiliséé pour determiner la pertinence d'un couple SR/OV à partir de la motivation et des ressources disponibles pour qu'un acteur accomplisse un certain objectif.
A6: Matrice Motivation × Ressources → Pertinence
B8: RESSOURCES (ressources financières, compétences cyber, outillage, temps)
A9: MOTIVATION | B9: Ressources limitées | C9: Ressources significatives | D9: Ressources importantes | E9: Ressources illimitées
A10: Fortement motivé | B10: Moyennement pertinent | C10: Plutôt pertinent | D10: Très pertinent | E10: Très pertinent
A11: Assez motivé | B11: Moyennement pertinent | C11: Plutôt pertinent | D11: Plutôt pertinent | E11: Très pertinent
A12: Peu motivé | B12: Peu pertinent | C12: Moyennement pertinent | D12: Plutôt pertinent | E12: Plutôt pertinent
A13: Très peu motivé | B13: Peu pertinent | C13: Peu pertinent | D13: Moyennement pertinent | E13: Moyennement pertinent
A15: Définition des niveaux de motivation
A16: Niveau | B16: Définition
A17: Fortement motivé | B17: Enjeu personnel direct, gain financier élevé, idéologie forte, intérêt stratégique majeur. La source poursuivra son objectif coûte que coûte.
A18: Assez motivé | B18: Enjeu réel mais non vital. La source poursuivra son objectif si l'opportunité s'offre, mais pas à tout prix.
A19: Peu motivé | B19: Intérêt opportuniste, défi ponctuel, curiosité. La source attaque si l'attaque est facile, sinon abandonne.
A20: Très peu motivé | B20: Pas d'intérêt direct envers l'objet d'étude. L'organisation pourrait être affectée comme dommage collatéral d'une attaque non ciblée.
A22: Définition des niveaux de ressources
A23: Niveau | B23: Définition
A24: Ressources limitées | B24: Outillage standard (Kali, scripts publics), compétences faibles à moyennes, temps disponible limité, pas de ressources financières dédiées à l'attaque.
A25: Ressources significatives | B25: Outillage avancé, compétences intermédiaires à fortes, temps disponible important. Profil typique : groupe organisé sans soutien étatique, insider qualifié, hacktiviste structuré.
A26: Ressources importantes | B26: Infrastructure d'attaque dédiée (C2, kits sur-mesure), compétences fortes, ressources financières conséquentes. Profil typique : groupe cybercriminel organisé (RaaS).
A27: Ressources illimitées | B27: Capacités étatiques type APT : 0-days, ressources humaines et financières quasi sans limite, opérations longue durée, supply-chain attacks possibles.
A29: Définition des niveaux de pertinence et décision associée
A30: Pertinence | B30: Signification | D30: Décision suggérée
A31: Peu pertinent | B31: Couple théoriquement possible mais peu susceptible de se concrétiser : motivation faible et/ou ressources insuffisantes. | D31: Écarté
A32: Moyennement pertinent | B32: Couple plausible mais non prioritaire. Mérite d'être surveillé pour détecter une évolution. | D32: Surveillance
A33: Plutôt pertinent | B33: Couple probable à intégrer dans l'analyse des scénarios stratégiques (atelier 3). | D33: Retenu
A34: Très pertinent | B34: Couple hautement probable à intégrer prioritairement dans les scénarios stratégiques. | D34: Retenu

Sheet A2.1 Sources de risque
A1: A2.1 - Sources de risque
A4: Liste des sources de risque identifiés au regard de l'entité Unicampus+. Cette liste (qui n'est pas en elle-même un livrable de l'atlier 2) sert à l'établissement des couples SR/OV. Nous notons qu'ils ne nous a pas parru pertinant de considerer les erreurs humaines comme une source de risque, ces dernières n'ayant aucune motivation ni capacité propre.
A6: Typologie des sources de risque retenues pour UniCampus+
A7: Code SR | B7: Libellé | C7: Profil | D7: Description et profil sociologique | E7: Capacités typiques
A8: SR-A | B8: Étudiant malveillant | C8: Interne | D8: Étudiant inscrit à UniCampus+. Profil hétérogène sur 12 000 individus : une fraction non négligeable dispose de compétences cyber réelles (Master Info, double cursus, autoformation). Bénéficie d'un accès physique au campus et au WiFi étudiants. Motivation typiquement personnelle (notes, examens) ou de défi. | E8: Motivation variable selon l'OV ; ressources globalement significatives (compétences disponibles, temps illimité, accès interne).
A9: SR-B | B9: Cybercriminel organisé | C9: Externe | D9: Groupe cybercriminel à objectif financier (ransomware-as-a-service, revente de données). Cible opportuniste : UniCampus+ représente une cible attractive (budget public, données nombreuses, sécurité historiquement faible dans l'ESR français). | E9: Motivation forte (gain financier) ; ressources importantes (kits ransomware matures, infrastructure C2).
A10: SR-C | B10: Acteur étatique / concurrent (APT) | C10: Externe | D10: Service de renseignement étranger ou concurrent industriel ciblant le patrimoine scientifique d'UniCampus+. Pertinence dépendant du caractère stratégique des recherches conduites (dual-use, IA, biotech, cryptographie…). | E10: Motivation modérée à forte selon les domaines de recherche ; ressources illimitées (APT, supply-chain, 0-days).
A11: SR-D | B11: Hacktiviste | C11: Externe | D11: Individu ou collectif motivé par une cause idéologique (transparence, justice sociale, animaux de laboratoire, partenariats industriels controversés). Capable d'attaques médiatisées (défacement, fuites volontaires). | E11: Motivation variable selon les causes pertinentes vis-à-vis d'UniCampus+ ; ressources significatives (compétences réelles, outillage public et privé).
A12: SR-E | B12: Personnel mécontent ou ex-personnel | C12: Interne ou ex-interne | D12: Membre ou ancien membre du personnel administratif, enseignant ou DSI, agissant par vengeance, fraude personnelle ou en réaction à un licenciement, une sanction ou un conflit. Bénéficie d'un accès légitime ou résiduel (compte non révoqué) et d'une connaissance fine du SI. | E12: Motivation modérée à forte selon le contexte (fraude RH, vengeance) ; ressources significatives (accès interne, connaissance du SI).

Sheet A2.2 Couples SR-OV
A1: A2.2 - Couples Source de risque / Objectif visé
A4: Première sortie de l'atelier 2 : Tableau des couples SR/OV évalués pour UniCampus+.
A6: Liste des couples SR/OV évalués
A7: Code couple | B7: Source de risque | C7: Objectif visé | D7: Motivation | E7: Ressources | F7: Pertinence (calculée) | G7: Décision | H7: ER ciblé(s)
A8: C01 | B8: SR-A Étudiant malveillant | C8: Compromettre les résultats académiques (modifier notes, voler sujets d'examen) | D8: Fortement motivé | E8: Ressources significatives | F8: =IFERROR(INDEX('A2.0 Échelle de pertinence'!$B$10:$E$13,MATCH(D8,'A2.0 Échelle de pertinence'!$A$10:$A$13,0),MATCH(E8,'A2.0 Échelle de pertinence'!$B$9:$E$9,0)),"") -> Plutôt pertinent | G8: Retenu | H8: ER03
A9: C02 | B9: SR-A Étudiant malveillant | C9: Sabotage opportuniste (défi, curiosité, perturbation d'une session d'examens) | D9: Peu motivé | E9: Ressources significatives | F9: =IFERROR(INDEX('A2.0 Échelle de pertinence'!$B$10:$E$13,MATCH(D9,'A2.0 Échelle de pertinence'!$A$10:$A$13,0),MATCH(E9,'A2.0 Échelle de pertinence'!$B$9:$E$9,0)),"") -> Moyennement pertinent | G9: Surveillance | H9: ER04, ER08
A10: C03 | B10: SR-B Cybercriminel organisé | C10: Extorquer une rançon par chiffrement de l'infrastructure | D10: Fortement motivé | E10: Ressources importantes | F10: =IFERROR(INDEX('A2.0 Échelle de pertinence'!$B$10:$E$13,MATCH(D10,'A2.0 Échelle de pertinence'!$A$10:$A$13,0),MATCH(E10,'A2.0 Échelle de pertinence'!$B$9:$E$9,0)),"") -> Très pertinent | G10: Retenu | H10: ER06, ER04
A11: C04 | B11: SR-B Cybercriminel organisé | C11: Revendre les données personnelles des étudiants et personnels sur le marché noir | D11: Assez motivé | E11: Ressources importantes | F11: =IFERROR(INDEX('A2.0 Échelle de pertinence'!$B$10:$E$13,MATCH(D11,'A2.0 Échelle de pertinence'!$A$10:$A$13,0),MATCH(E11,'A2.0 Échelle de pertinence'!$B$9:$E$9,0)),"") -> Plutôt pertinent | G11: Retenu | H11: ER01
A12: C05 | B12: SR-C Acteur étatique / concurrent | C12: Exfiltrer le patrimoine scientifique stratégique des laboratoires | D12: Assez motivé | E12: Ressources illimitées | F12: =IFERROR(INDEX('A2.0 Échelle de pertinence'!$B$10:$E$13,MATCH(D12,'A2.0 Échelle de pertinence'!$A$10:$A$13,0),MATCH(E12,'A2.0 Échelle de pertinence'!$B$9:$E$9,0)),"") -> Très pertinent | G12: Retenu | H12: ER02
A13: C06 | B13: SR-D Hacktiviste | C13: Publier des données personnelles pour discréditer l'institution | D13: Peu motivé | E13: Ressources significatives | F13: =IFERROR(INDEX('A2.0 Échelle de pertinence'!$B$10:$E$13,MATCH(D13,'A2.0 Échelle de pertinence'!$A$10:$A$13,0),MATCH(E13,'A2.0 Échelle de pertinence'!$B$9:$E$9,0)),"") -> Moyennement pertinent | G13: Surveillance | H13: ER01
A14: C07 | B14: SR-D Hacktiviste | C14: Défacer la plateforme Moodle ou saboter l'image institutionnelle | D14: Peu motivé | E14: Ressources significatives | F14: =IFERROR(INDEX('A2.0 Échelle de pertinence'!$B$10:$E$13,MATCH(D14,'A2.0 Échelle de pertinence'!$A$10:$A$13,0),MATCH(E14,'A2.0 Échelle de pertinence'!$B$9:$E$9,0)),"") -> Moyennement pertinent | G14: Surveillance | H14: ER04, ER08
A15: C08 | B15: SR-E Personnel mécontent ou ex-personnel | C15: Détourner la paie ou frauder le système de gestion RH | D15: Assez motivé | E15: Ressources significatives | F15: =IFERROR(INDEX('A2.0 Échelle de pertinence'!$B$10:$E$13,MATCH(D15,'A2.0 Échelle de pertinence'!$A$10:$A$13,0),MATCH(E15,'A2.0 Échelle de pertinence'!$B$9:$E$9,0)),"") -> Plutôt pertinent | G15: Retenu | H15: ER05
A16: C09 | B16: SR-E Personnel mécontent ou ex-personnel | C16: Détruire ou altérer des données par vengeance | D16: Assez motivé | E16: Ressources significatives | F16: =IFERROR(INDEX('A2.0 Échelle de pertinence'!$B$10:$E$13,MATCH(D16,'A2.0 Échelle de pertinence'!$A$10:$A$13,0),MATCH(E16,'A2.0 Échelle de pertinence'!$B$9:$E$9,0)),"") -> Plutôt pertinent | G16: Retenu | H16: ER05, ER09

Sheet A2.3 Liens couples - ER
A1: A2.3 - Liens entre les couples SR/OV et les événements redoutés
A4: Seconde sortie de l'atlier 2 : Lien entre les différents couples SR//OV et les ER. Ce tableau est l'équivalent du visuel de la slide 32 du cours. Lecture : Pour chaque ER, on liste les couples qui le portent avec leur pertinence par gravité descendante.
A6: Couples SR/OV portant chaque événement redouté (triés par gravité descendante)
A7: Code ER | B7: Événement redouté | C7: Gravité | D7: Code couple | E7: Couple SR/OV | F7: Pertinence
A8: ER01 | B8: Fuite massive des données personnelles des étudiants et personnels | C8: G4 | D8: C04 | E8: SR-B Cybercriminel × Revente de données personnelles | F8: Plutôt pertinent
D9: C06 | E9: SR-D Hacktiviste × Publication de données pour discrédit | F9: Moyennement pertinent
A10: ER06 | B10: Interruption massive et simultanée de l'ensemble des services numériques | C10: G4 | D10: C03 | E10: SR-B Cybercriminel × Extorsion par rançongiciel | F10: Très pertinent
A11: ER02 | B11: Fuite des données et résultats de recherche | C11: G3 | D11: C05 | E11: SR-C Acteur étatique × Exfiltration du patrimoine scientifique | F11: Très pertinent
A12: ER03 | B12: Altération frauduleuse des notes, moyennes ou diplômes | C12: G3 | D12: C01 | E12: SR-A Étudiant × Compromission des résultats académiques | F12: Plutôt pertinent
A13: ER04 | B13: Interruption de l'accès aux services pédagogiques > 24 h (notamment examens) | C13: G3 | D13: C03 | E13: SR-B Cybercriminel × Extorsion par rançongiciel (effet de bord) | F13: Très pertinent
D14: C02 | E14: SR-A Étudiant × Sabotage opportuniste | F14: Moyennement pertinent
D15: C07 | E15: SR-D Hacktiviste × Défacement / sabotage image | F15: Moyennement pertinent
A16: ER05 | B16: Altération frauduleuse de la paie et des données RH | C16: G3 | D16: C08 | E16: SR-E Personnel mécontent × Détournement de la paie | F16: Plutôt pertinent
D17: C09 | E17: SR-E Personnel mécontent × Vengeance par destruction (volet RH) | F17: Plutôt pertinent
A18: ER09 | B18: Perte ou destruction définitive des données de recherche | C18: G3 | D18: C09 | E18: SR-E Personnel mécontent × Vengeance par destruction | F18: Plutôt pertinent
A19: ER08 | B19: Détournement de la messagerie pour campagnes externes malveillantes | C19: G2 | D19: C02 | E19: SR-A Étudiant × Sabotage opportuniste (volet mail) | F19: Moyennement pertinent
D20: C07 | E20: SR-D Hacktiviste × Défacement / sabotage image (volet mail) | F20: Moyennement pertinent

Sheet A3.0 Critères de dangerosité
A1: A3.0 - Critères d'évaluation de la dangerosité des parties prenantes
A4: Échelles d'évaluation des risques associés aux parties prenantes PP exterieurs (prestataires/ partenaires) en fonction des 4 critères vue dans le cours. Le premier tableau sert d'indication pour caractériser les différents niveaux de risques. Les deux tableaux suivants définissent des seuils precis utilisés pour les rendus de l'atelier 3.
A6: Échelles d'évaluation (4 niveaux par critère)
B7: EXPOSITION (taille de la bulle sur le radar) | D7: FIABILITÉ CYBER (couleur de la bulle sur le radar)
A8: Niveau | B8: Dépendance | C8: Pénétration | D8: Maturité cyber | E8: Confiance
A9: 1 | B9: Pas de lien avec le SI de la partie prenante pour réaliser la mission. | C9: Pas d'accès ou accès avec des privilèges de type utilisateur à des terminaux utilisateurs (poste de travail, ordiphone, etc.). | D9: Des règles d'hygiène sont appliquées ponctuellement et non formalisées. La capacité de réaction sur incident est incertaine. | E9: Les intentions de la partie prenante ne sont pas connues.
A10: 2 | B10: Lien avec le SI de la partie prenante utile à la réalisation de la mission. | C10: Accès avec privilèges de type administrateur à des terminaux utilisateurs (parc informatique, flotte de terminaux mobiles, etc.) ou accès physique aux bureaux de l'organisme. | D10: Les règles d'hygiène et la réglementation sont prises en compte, sans intégration dans une politique globale. La sécurité numérique est assurée selon un mode réactif. | E10: Les intentions de la partie prenante sont considérées comme neutres.
A11: 3 | B11: Lien avec le SI de la partie prenante indispensable mais non exclusif (possible substitution). | C11: Accès avec privilèges de type administrateur à des serveurs « métier » (serveur de fichiers, bases de données, serveur web, serveur d'application, etc.). | D11: Une politique globale est appliquée en matière de sécurité numérique. Celle-ci est assurée selon un mode réactif, avec une recherche de centralisation et d'anticipation sur certains risques. | E11: Les intentions de la partie prenante sont connues et probablement positives.
A12: 4 | B12: Lien avec le SI de la partie prenante indispensable et unique (pas de substitution possible). | C12: Accès avec privilèges de type administrateur à des équipements d'infrastructure (annuaires d'entreprise, DNS, DHCP, switchs, pare-feu, hyperviseurs, baies de stockage, etc.) ou accès physique aux salles serveurs de l'organisme. | D12: La partie prenante met en œuvre une politique de management du risque. La politique est intégrée et prend pleinement en compte une dimension proactive. | E12: Les intentions de la partie prenante sont parfaitement connues et pleinement compatibles avec celles de l'organisation étudiée.
A14: Seuils des zones de dangerosité (issus du guide ANSSI p.47)
A15: Zone | B15: Couleur | C15: Borne inférieure | D15: Borne supérieure | E15: Interprétation
A16: Veille | B16: Vert | C16: 0 | D16: 0,2 | E16: Niveau de dangerosité acceptable, surveillance simple.
A17: Contrôle | B17: Jaune / Orange | C17: 0,2 | D17: 2,5 | E17: Niveau de dangerosité modéré, mesures de contrôle à maintenir et renforcer si nécessaire.
A18: Danger | B18: Rouge | C18: 2,5 | D18: 16 (max) | E18: Partie prenante critique (PPC) : intégration prioritaire aux scénarios stratégiques et mesures de réduction.
A20: Paliers d'agrégation (taille et couleur des bulles sur le radar)
A21: Critère | B21: Palier 1 | C21: Palier 2 | D21: Palier 3 | E21: Palier 4
A22: EXPOSITION (D × P) | B22: < 3 | C22: 3 à 6 | D22: 7 à 9 | E22: > 9
A23: FIABILITÉ CYBER (M × C) | B23: < 4 | C23: 4 à 5 | D23: 6 à 7 | E23: > 7

Sheet A3.1 Parties prenantes
A1: A3.1 - Parties prenantes de l'écosystème d'UniCampus+
A4: Rendu de l'atelier 3 : Liste des parties prenantes (PP) externes identifiées dans l'écosystème d'UniCampus+.
A6: Typologie des parties prenantes de l'écosystème
A7: Code PP | B7: Catégorie | C7: Libellé | D7: Description et nature de la relation | E7: Interaction avec UniCampus+
A8: PA1 | B8: Partenaire | C8: Laboratoires de recherche partenaires | D8: Autres établissements de recherche (universités, EPIC, EPST) avec lesquels les laboratoires d'UniCampus+ co-publient, partagent des données scientifiques et conduisent des projets communs (ANR, projets européens). | E8: Partage de données de recherche (NFS / Samba), comptes invités, conventions de collaboration.
A9: PA2 | B9: Partenaire | C9: Partenaires industriels et financeurs | D9: Entreprises co-finançant des projets de recherche bilatéraux, chaires industrielles, contrats CIFRE. Peuvent recevoir des livrables de recherche et fournir des données ou des moyens. | E9: Échanges de livrables, accès ponctuel aux résultats intermédiaires, contrats de propriété intellectuelle.
A10: PA3 | B10: Partenaire | C10: Ministère de l'Enseignement Supérieur (tutelle) | D10: Autorité de tutelle administrative et financière. Reçoit du reporting et opère des contrôles. Pas d'interconnexion SI directe mais transmission régulière de données institutionnelles. | E10: Reporting périodique, transmission de données agrégées (effectifs, indicateurs).
A11: PA4 | B11: Partenaire | C11: CNIL (régulateur RGPD) | D11: Autorité administrative indépendante de contrôle des données personnelles. Interaction réglementaire (notifications d'incidents, contrôles éventuels). | E11: Notifications d'incident sous 72 h, contrôles ponctuels, recommandations.
A12: PR1 | B12: Prestataire | C12: Éditeurs et mainteneurs logiciels | D12: Éditeurs des logiciels métier du SI : Moodle, application RH, OpenLDAP, Postfix/Dovecot. Fournissent les correctifs de sécurité et le support. Pas d'accès distant direct dans la maquette v1, mais peuvent intervenir en télémaintenance ponctuelle. | E12: Mises à jour, correctifs, support de niveau 2-3, télémaintenance occasionnelle.
A13: PR2 | B13: Prestataire | C13: RENATER (opérateur réseau de l'ESR) | D13: Opérateur du réseau national de l'enseignement supérieur et de la recherche français, assurant le raccordement Internet d'UniCampus+ et la fédération d'identités (Renater Identity Federation). | E13: Raccordement Internet, transit, services mutualisés (DNS, fédération d'identité).
A14: PR3 | B14: Prestataire | C14: Fournisseurs de bibliothèque numérique | D14: Fournisseurs externes de ressources documentaires accédées via la VM1.5 non instrumentée (Couperin, Cairn, EBSCO, ScienceDirect, etc.). Accès SSO/IP-based, hébergement chez le fournisseur. | E14: Accès aux ressources via IP filtering ou proxy d'authentification, transmission des historiques de consultation.

Sheet A3.2 Cartographie dangerosité
A1: A3.2 - Cartographie de dangerosité de l'écosystème
A4: Évaluation de chaque partie prenante sur les 4 critères de A3.0 (notes 1-4). Les colonnes Exposition (D×P), Fiabilité cyber (M×C) et Dangerosité ((D×P)/(M×C)) sont calculées par formule. La zone (Veille / Contrôle / Danger) résulte de la dangerosité et des seuils ANSSI (0,2 et 2,5). Les parties prenantes en zone Danger sont les Parties Prenantes Critiques (PPC) à intégrer prioritairement aux scénarios stratégiques de A3.3. Le radar ci-dessous reproduit le visuel des slides 35-37 du cours.
A6: Évaluation de la dangerosité des parties prenantes
A7: Code PP | B7: Libellé | C7: Dépendance (D) | D7: Pénétration (P) | E7: Exposition (D×P) | F7: Maturité (M) | G7: Confiance (C) | H7: Fiabilité (M×C) | I7: Dangerosité ((D×P)/(M×C)) | J7: Zone | K7: PPC ?
A8: PA1 | B8: Laboratoires de recherche partenaires | C8: 3 | D8: 3 | E8: =C8*D8 -> 9 | F8: 2 | G8: 3 | H8: =F8*G8 -> 6 | I8: =IFERROR(E8/H8,"") -> 1.5 | J8: =IF(I8="","",IF(I8<0.2,"Veille",IF(I8<2.5,"Contrôle","Danger"))) -> Contrôle | K8: =IF(J8="Danger","Oui","Non") -> Non
A9: PA2 | B9: Partenaires industriels et financeurs | C9: 2 | D9: 2 | E9: =C9*D9 -> 4 | F9: 3 | G9: 3 | H9: =F9*G9 -> 9 | I9: =IFERROR(E9/H9,"") -> 0.44444444 | J9: =IF(I9="","",IF(I9<0.2,"Veille",IF(I9<2.5,"Contrôle","Danger"))) -> Contrôle | K9: =IF(J9="Danger","Oui","Non") -> Non
A10: PA3 | B10: Ministère de l'Enseignement Supérieur | C10: 3 | D10: 1 | E10: =C10*D10 -> 3 | F10: 4 | G10: 4 | H10: =F10*G10 -> 16 | I10: =IFERROR(E10/H10,"") -> 0.1875 | J10: =IF(I10="","",IF(I10<0.2,"Veille",IF(I10<2.5,"Contrôle","Danger"))) -> Veille | K10: =IF(J10="Danger","Oui","Non") -> Non
A11: PA4 | B11: CNIL (régulateur RGPD) | C11: 1 | D11: 1 | E11: =C11*D11 -> 1 | F11: 4 | G11: 4 | H11: =F11*G11 -> 16 | I11: =IFERROR(E11/H11,"") -> 0.0625 | J11: =IF(I11="","",IF(I11<0.2,"Veille",IF(I11<2.5,"Contrôle","Danger"))) -> Veille | K11: =IF(J11="Danger","Oui","Non") -> Non
A12: PR1 | B12: Éditeurs et mainteneurs logiciels | C12: 3 | D12: 3 | E12: =C12*D12 -> 9 | F12: 2 | G12: 2 | H12: =F12*G12 -> 4 | I12: =IFERROR(E12/H12,"") -> 2.25 | J12: =IF(I12="","",IF(I12<0.2,"Veille",IF(I12<2.5,"Contrôle","Danger"))) -> Contrôle | K12: =IF(J12="Danger","Oui","Non") -> Non
A13: PR2 | B13: RENATER (opérateur réseau ESR) | C13: 4 | D13: 2 | E13: =C13*D13 -> 8 | F13: 4 | G13: 4 | H13: =F13*G13 -> 16 | I13: =IFERROR(E13/H13,"") -> 0.5 | J13: =IF(I13="","",IF(I13<0.2,"Veille",IF(I13<2.5,"Contrôle","Danger"))) -> Contrôle | K13: =IF(J13="Danger","Oui","Non") -> Non
A14: PR3 | B14: Fournisseurs de bibliothèque numérique | C14: 2 | D14: 1 | E14: =C14*D14 -> 2 | F14: 3 | G14: 3 | H14: =F14*G14 -> 9 | I14: =IFERROR(E14/H14,"") -> 0.22222222 | J14: =IF(I14="","",IF(I14<0.2,"Veille",IF(I14<2.5,"Contrôle","Danger"))) -> Contrôle | K14: =IF(J14="Danger","Oui","Non") -> Non
A16: Synthèse - Parties prenantes critiques (PPC)
A17: Les parties prenantes dont la colonne PPC indique « Oui » sont les Parties Prenantes Critiques (PPC) au sens ANSSI : elles seront intégrées prioritairement aux scénarios stratégiques de A3.3 et feront l'objet de mesures de sécurité spécifiques en A3.4. Les PP en zone Contrôle ne sont pas PPC mais doivent être surveillées. Au vue de cette analyse, aucune partie prenante n'est identifé comme critique. Cela peut se justifier par le fait que l'entité Unicampus, dans la modélisation que nous en avons faites est particulièrement autonome et dont les partenaires possède un niveau de confiance relativement élevé.
A19: Visualisation radar de la cartographie (équivalent slide 37 du cours et p.47 du guide ANSSI)

Sheet A3.3 Scénarios stratégiques
A1: A3.3 - Scénarios stratégiques
A4: Second rendu pour l'atelier 3 : Pour chaque couple SR/OV Retenu en A2.2, on construit un scénario stratégique de haut niveau qui décrit 1 à 3 chemins d'attaque (attaque directe ou rebond via une PPC). Format inspiré du guide ANSSI p.52. La gravité est héritée de l'événement redouté associé en A1.4 (slide 32 du cours). Les chemins par rebond ciblent en priorité les parties prenantes en zone de danger ou de contrôle élevée identifiées en A3.2. Les scénarios stratégiques retenus ici servent d'entrée à l'atelier 4 (scénarios opérationnels).
A6: Scénarios stratégiques retenus (un par couple SR/OV)
A7: Code scénario | B7: Code SR/OV | C7: Source de risque | D7: Objectif visé | E7: Chemins d'attaque stratégiques | F7: Gravité | G7: ER associé(s)
A8: SS1 | B8: C01 | C8: SR-A Étudiant malveillant | D8: Compromettre les résultats académiques (modifier notes, voler sujets d'examen) | E8: Un étudiant compromet ses propres résultats académiques : 1. en exploitant directement, depuis le WiFi étudiant, les services pédagogiques internes (la plateforme Moodle et l'annuaire d'identité sont accessibles sans cloisonnement) ; 2. par usurpation d'identité d'un enseignant après vol de credentials (réutilisation, phishing ciblé) — chemin pivot vers ER07. | F8: G3 | G8: ER03
A9: SS2 | B9: C03 | C9: SR-B Cybercriminel organisé | D9: Extorquer une rançon par chiffrement de l'infrastructure | E9: Un cybercriminel paralyse l'établissement par rançongiciel : 1. par phishing ciblé du personnel (attaque directe la plus fréquente dans l'ESR français) ; 2. par rebond via un éditeur ou mainteneur logiciel compromis (PR1) — supply chain attack sur un correctif ou une mise à jour de Moodle, application RH ou autre composant ; 3. par exploitation d'une vulnérabilité connue non patchée sur un service exposé en façade Internet. | F9: G4 | G9: ER06, ER04
A10: SS3 | B10: C04 | C10: SR-B Cybercriminel organisé | D10: Revendre des données personnelles des étudiants et personnels | E10: Un cybercriminel exfiltre la base de données personnelles pour revente : 1. par exploitation directe d'une vulnérabilité applicative ou d'un bind LDAP anonyme depuis Internet ; 2. par rebond via un éditeur logiciel compromis (PR1) ayant accès en télémaintenance. | F10: G4 | G10: ER01
A11: SS4 | B11: C05 | C11: SR-C Acteur étatique / concurrent | D11: Exfiltrer le patrimoine scientifique stratégique | E11: Un acteur étatique vole les travaux de recherche : 1. par compromission directe du serveur de calcul et stockage de recherche depuis Internet ; 2. par rebond via un laboratoire de recherche partenaire (PA1) moins bien sécurisé qui détient des copies des données partagées (chemin similaire à l'exemple p.52 du guide ANSSI) ; 3. par rebond via un partenaire industriel (PA2) ayant accès à des livrables intermédiaires. | F11: G3 | G11: ER02
A12: SS5 | B12: CR08 | C12: SR-E Personnel mécontent ou ex-personnel | D12: Détourner la paie ou frauder le système de gestion RH | E12: Un personnel mécontent fraude le système RH : 1. depuis le réseau interne, en utilisant un compte légitime non révoqué pour modifier les éléments de paie ou les RIB de versement ; 2. par exploitation d'une vulnérabilité applicative de l'application RH. | F12: G3 | G12: ER05
A13: SS6 | B13: CR09 | C13: SR-E Personnel mécontent ou ex-personnel | D13: Détruire ou altérer des données par vengeance | E13: Un personnel mécontent détruit les données pour se venger : 1. en supprimant ou chiffrant les données sur les serveurs accessibles avec son compte (RH, recherche) ; 2. par rebond via un laboratoire partenaire (PA1) auquel il avait accès, pour atteindre des données partagées encore en cours. | F13: G3 | G13: ER05, ER09

Sheet A3.4 Mesures écosystème
A1: A3.4 - Mesures de sécurité sur l'écosystème
A4: Mesures organisationnelles, contractuelles et techniques portant sur les parties prenantes critiques (PPC) identifiées en A3.2 et impliquées dans les scénarios stratégiques de A3.3. Format inspiré du guide ANSSI p.54. Pour chaque PPC, on précise les chemins d'attaque associés, les mesures à mettre en place, la dangerosité initiale et la dangerosité résiduelle estimée après mise en œuvre. Selon le guide ANSSI (p.53), la dangerosité résiduelle n'est utilisable que si la mesure est effectivement mise en œuvre avant la suite de l'analyse. Les mesures internes à UniCampus+ (durcissement maquette) seront traitées en atelier 5.
A6: Mesures de sécurité pour les parties prenantes critiques
A7: Code PP | B7: Partie prenante | C7: Chemins d'attaque stratégiques | D7: Mesures de sécurité | E7: Dangerosité initiale | F7: Dangerosité résiduelle
A8: PR1 | B8: Éditeurs et mainteneurs logiciels | C8: Déploiement de rançongiciel par supply-chain (SS2 chemin 2) ; exfiltration de données via télémaintenance (SS3 chemin 2) | D8: Accroître la maturité cyber et la confiance des prestataires logiciels : • inclure dans les contrats des clauses cyber (RGPD, notification d'incident < 72 h, audit de sécurité périodique, droit d'audit) ; • vérifier la signature des correctifs et mises à jour avant déploiement ; • imposer un accès distant via un canal authentifié et journalisé (suppression de tout accès permanent non maîtrisé) ; • exiger une attestation de conformité (ISO 27001 ou équivalent) pour les éditeurs de logiciels métier sensibles (RH notamment). Effet attendu : Maturité 2 → 3, Confiance 2 → 3 | E8: 2.25 | F8: 1
A9: PA1 | B9: Laboratoires de recherche partenaires | C9: Exfiltration du patrimoine scientifique par rebond (SS4 chemin 2) ; destruction collatérale par personnel mécontent (SS6 chemin 2) | D9: Diminuer la pénétration des laboratoires partenaires et accroître leur maturité cyber : • limiter strictement le partage de données au juste besoin (principe du moindre privilège) actuellement, les données partagées via NFS/Samba sont accessibles trop largement ; • cloisonner les espaces de partage par projet / convention ; • inclure dans les conventions de collaboration des clauses sur la sécurité des données (chiffrement, traçabilité, notification d'incident) ; • organiser des audits croisés ponctuels sur les partages de données les plus sensibles. Effet attendu : Pénétration 3 → 2. | E9: 1.5 | F9: 1
A10: PA2 | B10: Partenaires industriels et financeurs | C10: Exfiltration du patrimoine scientifique par rebond (SS4 chemin 3) | D10: Encadrer contractuellement la diffusion des livrables intermédiaires : • transmission de livrables uniquement sous forme contractuellement définie (versionnage, filigrane numérique, restrictions d'usage) ; • clause de confidentialité renforcée ; • transmission via canaux chiffrés exclusivement (suppression du mail en clair pour les livrables). Effet attendu : Confiance 3 → 4 (intentions parfaitement connues et compatibles). | E10: 0.44 | F10: 0.33
A11: PR3 | B11: Fournisseurs de bibliothèque numérique | C11: Hors scénarios principaux ; vigilance générale (VM1.5 non instrumentée) | D11: Mesures préventives génériques : • contrôler la liste des fournisseurs et leur fédération d'identité ; • vérifier la non-transmission de données personnelles aux fournisseurs au-delà du strict nécessaire (consultation anonymisée si possible) ; • revoir périodiquement les contrats et leurs clauses RGPD. | E11: 0.22 | F11: 0.22
A13: Synthèse de l'effet des mesures sur l'écosystème
A14: Les mesures listées ci-dessus visent à ramener la dangerosité de l'ensemble des parties prenantes sous le seuil de 1,0 (milieu de la zone de contrôle), conformément à une politique de gestion conservatrice des relations avec l'écosystème. Aucune partie prenante n'est en zone de danger (≥ 2,5) dans la situation initiale, ce qui s'explique par le caractère auto-hébergé d'UniCampus+ et l'absence d'infogérance critique. Le risque résiduel principal reste interne (couvert à l'atelier 5) et non écosystémique.

Sheet A4.0 Échelle vraisemblance
A1: A4.0 - Échelle de vraisemblance des scénarios opérationnels
A4: Échelle de vraisemblance V1 à V4 issue du guide ANSSI EBIOS RM (p.66) et de la slide 46 du cours. Cette échelle évalue la probabilité de succès ou la faisabilité d'un scénario opérationnel, en confrontant les ressources et la motivation présumées de la source de risque d'une part, et le socle de sécurité et le niveau de vulnérabilité de l'objet étudié d'autre part. La vraisemblance est évaluée directement (méthode expresse ANSSI) pour chacun des 6 scénarios opérationnels de A4.1.
A6: Échelle V1 à V4
A7: Niveau | B7: Libellé | C7: Description
A8: V1 | B8: Peu vraisemblable | C8: La source de risque a peu de chance d'atteindre son objectif visé selon l'un des modes opératoires envisagés. La vraisemblance du scénario est faible.
A9: V2 | B9: Vraisemblable | C9: La source de risque est susceptible d'atteindre son objectif visé selon l'un des modes opératoires envisagés. La vraisemblance du scénario est significative.
A10: V3 | B10: Très vraisemblable | C10: La source de risque va probablement atteindre son objectif visé selon l'un des modes opératoires envisagés. La vraisemblance du scénario est élevée.
A11: V4 | B11: Certain ou déjà produit | C11: La source de risque va certainement atteindre son objectif visé selon l'un des modes opératoires envisagés OU un tel scénario s'est déjà produit au sein de l'organisation (historique d'incidents).

Sheet A4.1 Graphes d'attaque
A1: A4.1 - Scénarios opérationnels et graphes d'attaque
A4: Pour chacun des 6 scénarios stratégiques retenus en A3.3, un scénario opérationnel (SO) détaille les procédures techniques susceptibles d'être mises en œuvre par la source de risque. Chaque scénario est structuré selon la séquence d'attaque type CONNAÎTRE → RENTRER → TROUVER → EXPLOITER (slide 44 du cours, p.62-63 du guide ANSSI). Le chemin retenu pour l'analyse est mis en évidence par des flèches rouges ; les chemins alternatifs possibles sont représentés en gris. La méthode de cotation de la vraisemblance utilisée est l'estimation globale directe (méthode expresse ANSSI, p.65). Les biens supports critiques (BSC) et les vulnérabilités spécifiques exploitées sont listés sous chaque graphe.
A6: SO1 - Étudiant malveillant compromet les résultats académiques (parent SS1, gravité G3, vraisemblance V3)
B37: Biens supports critiques (BSC) | C37: Vulnérabilités spécifiques exploitées
B38: • BS01 Moodle • BS02 BDD Moodle • BS04 LDAP • BS13 Réseau campus | C38: • Bind LDAP anonyme sur uc-srv-ldap (slapd sans TLS) • WiFi étudiant et serveurs sur le même VLAN 192.168.107.0/24 (pas de cloisonnement) • Pas de MFA ni de rate-limit sur Moodle • Aucun log centralisé : modification non détectable a posteriori
A40: SO2 - Cybercriminel déploie un rançongiciel (parent SS2, gravité G4, vraisemblance V4)
B71: Biens supports critiques (BSC) | C71: Vulnérabilités spécifiques exploitées
B72: • BS01 Moodle • BS05 Web RH • BS07 BDD RH • BS08 Mail • BS10 NFS recherche • BS13 Réseau campus | C72: • Clé SSH d'admin DSI stockée en clair sur uc-poste-dsi (/home/ubuntu/.ssh/) • Sudo NOPASSWD pour ubuntu sur toutes les VMs • VPN PPTP legacy avec MPPE-128 (RC4 déprécié) et compte partagé (campus/unicampus2024) • Aucun cloisonnement réseau : un seul VLAN pour serveurs et postes • Pas de sauvegarde immuable (ni offline) -> rançon = seule option de récupération
A74: SO3 - Cybercriminel exfiltre les données personnelles (parent SS3, gravité G4, vraisemblance V3)
B105: Biens supports critiques (BSC) | C105: Vulnérabilités spécifiques exploitées
B106: • BS05 Web RH • BS07 BDD RH • BS04 LDAP • BS01 Moodle | C106: • Injection SQL non corrigée dans le portail uc-web-rh • uc-db-rh MariaDB exposée 0.0.0.0:3306, hashs en SHA1 sans sel • HTTP en clair sur uc-web-rh (capture credentials triviale) • Bind LDAP anonyme expose la liste complète des comptes • Pas de détection d'exfiltration (logs locaux non centralisés)
A108: SO4 - Acteur étatique exfiltre le patrimoine scientifique (parent SS4, gravité G3, vraisemblance V2)
B139: Biens supports critiques (BSC) | C139: Vulnérabilités spécifiques exploitées
B140: • BS09 calc-recherche • BS10 NFS recherche • BS11 PostgreSQL recherche • BS12 Postes recherche | C140: • NFS et Samba exposés sans authentification sur uc-calc-recherche • Jupyter sans token ni mot de passe sur 0.0.0.0:8888 • Pas de cloisonnement entre VLAN UniCampus et infrastructure des partenaires • Données scientifiques sensibles stockées en clair, sans classification • Aucune supervision capable de détecter une exfiltration low-and-slow
A142: SO5 - Personnel mécontent détourne la paie (parent SS5, gravité G3, vraisemblance V2)
B173: Biens supports critiques (BSC) | C173: Vulnérabilités spécifiques exploitées
B174: • BS05 Web RH • BS07 BDD RH | C174: • Pas de séparation des privilèges côté application RH (un seul rôle) • Comptes non révoqués au départ (pas de processus IAM) • Aucune validation à 4 yeux pour la modification de RIB / salaire • Pas de journal d'audit applicatif des modifications RH
A176: SO6 - Personnel mécontent détruit par vengeance (parent SS6, gravité G3, vraisemblance V2)
B207: Biens supports critiques (BSC) | C207: Vulnérabilités spécifiques exploitées
B208: • BS05 Web RH • BS07 BDD RH • BS09 calc-recherche • BS10 NFS recherche | C208: • Sudo NOPASSWD pour ubuntu sur toutes les VMs (élévation triviale) • Compte VPN partagé jamais changé (présent dans email DSI exfiltrable) • Aucune sauvegarde immuable hors-ligne : suppression = perte définitive • Pas de contrôle d'accès granulaire sur les partages NFS recherche

Sheet A4.2 Synthèse vraisemblance
A1: A4.2 - Synthèse des scénarios opérationnels et de leur vraisemblance
A4: Tableau récapitulatif des 6 scénarios opérationnels (format inspiré de la slide 47 du cours et de la p.67 du guide ANSSI). Pour chaque scénario : la gravité héritée du scénario stratégique parent (A3.3), la vraisemblance globale évaluée en A4.1, et le couple (gravité, vraisemblance) qui sera utilisé en A5 pour positionner les risques sur la matrice de traitement.
A6: Récapitulatif gravité × vraisemblance
A7: Code SO | B7: Source de risque | C7: Chemin d'attaque retenu (synthèse) | D7: Gravité | E7: Vraisemblance | F7: Niveau de risque (G × V)
A8: SO1 | B8: SR-A Étudiant malveillant | C8: C: Scan VLAN 192.168.107.0/24 depuis WiFi étudiant → R: Phishing ciblé d'un enseignant (pièce jointe piégée) → T: Connexion Moodle avec credentials enseignant → E: Modification des notes dans mdl_grade_* | D8: G3 | E8: V3 | F8: Modéré (9)
A9: SO2 | B9: SR-B Cybercriminel organisé | C9: C: OSINT sur le personnel (LinkedIn, site web) → R: Phishing ciblé du personnel (pièce jointe macro) → T: Vol clé SSH en clair sur uc-poste-dsi (/home/.ssh/) → E: Chiffrement simultané Moodle / RH / Recherche / Mail | D9: G4 | E9: V4 | F9: Élevé (16)
A10: SO3 | B10: SR-B Cybercriminel organisé | C10: C: Port scan externe (identification uc-web-rh) → R: Injection SQL sur uc-web-rh (login bypass) → T: Lecture directe uc-db-rh (écoute 0.0.0.0:3306) → E: Exfiltration base RH complète (500 personnels) | D10: G4 | E10: V3 | F10: Élevé (12)
A11: SO4 | B11: SR-C Acteur étatique / concurrent | C11: C: Reconnaissance longue durée labos partenaires → R: Compromission labo partenaire PA1 (maillon faible) → T: Accès NFS/Samba partenaire (données partagées) → E: Exfiltration lente et discrète (low and slow) | D11: G3 | E11: V2 | F11: Modéré (6)
A12: SO5 | B12: SR-E Personnel mécontent ou ex-personnel | C12: C: Connaissance interne du SI RH (personnel actif/ex) → R: Compte légitime actif → T: Navigation directe uc-web-rh (credentials valides) → E: Modification RIB de versement (détournement) | D12: G3 | E12: V2 | F12: Modéré (6)
A13: SO6 | B13: SR-E Personnel mécontent ou ex-personnel | C13: C: Connaissance interne du SI (personnel mécontent) → R: Compte légitime actif → T: Accès direct serveurs avec privilèges utilisateur → E: Suppression données critiques (RH, recherche) | D13: G3 | E13: V2 | F13: Modéré (6)

Sheet A5.0 Matrice et acceptation
A1: A5.0 - Matrice de risque et classes d'acceptation
A4: Cette matrice 4×4 croise la gravité (G1 à G4) issue de A1.3 avec la vraisemblance (V1 à V4) issue de A4.0. Le niveau de risque correspondant est calculé par le produit G × V. Trois classes d'acceptabilité ANSSI (p.74 du guide) déterminent la stratégie de traitement : Faible (acceptable en l'état), Moyen (tolérable sous contrôle), Élevé (inacceptable). La matrice ci-dessous sert de référence pour positionner les 6 risques R01-R06 d'UniCampus+ (cartographies en A5.1).
A6: Matrice gravité × vraisemblance (niveau de risque = G × V)
A7: G \ V | B7: V1 | C7: V2 | D7: V3 | E7: V4 | F7: Interprétation
A8: G4 - Critique | B8: 4 (Faible) | C8: 8 (Moyen) | D8: 12 (Élevé) | E8: 16 (Élevé) | F8: Incapacité d'assurer la mission, survie menacée
A9: G3 - Grave | B9: 3 (Faible) | C9: 6 (Moyen) | D9: 9 (Moyen) | E9: 12 (Élevé) | F9: Forte dégradation, surmonté avec sérieuses difficultés
A10: G2 - Significative | B10: 2 (Faible) | C10: 4 (Faible) | D10: 6 (Moyen) | E10: 8 (Moyen) | F10: Dégradation, surmonté avec quelques difficultés
A11: G1 - Mineure | B11: 1 (Faible) | C11: 2 (Faible) | D11: 3 (Faible) | E11: 4 (Faible) | F11: Aucun impact significatif
A13: Classes d'acceptabilité du risque (ANSSI p.74)
A14: Niveau | B14: Couleur | C14: Score G × V | D14: Acceptabilité | E14: Décision | F14: Actions à mener
A15: Faible | B15: Vert | C15: ≤ 4 | D15: Acceptable en l'état | E15: Accepter | F15: Aucune action n'est à entreprendre
A16: Moyen | B16: Orange | C16: 5 à 9 | D16: Tolérable sous contrôle | E16: Réduire / Surveiller | F16: Un suivi en termes de gestion du risque est à mener et des actions sont à mettre en place dans le cadre d'une amélioration continue
A17: Élevé | B17: Rouge | C17: ≥ 10 | D17: Inacceptable | E17: Réduire impérativement | F17: Des mesures de réduction du risque doivent impérativement être prises à court terme. Dans le cas contraire, tout ou partie de l'activité sera refusé

Sheet A5.1 Cartographies du risque
A1: A5.1 - Cartographies du risque initial et résiduel
A4: Les 6 risques R01-R06 (un par scénario opérationnel d'A4) sont positionnés sur la matrice gravité × vraisemblance avant traitement (cartographie initiale) et après application complète des mesures du plan de traitement A5.3 (cartographie résiduelle). Le déplacement des risques vers la zone Faible (verte) démontre l'efficacité du plan. Format inspiré des slides 49-50 du cours.
A6: Tableau comparatif des 6 risques (initial vs résiduel)
A7: Code | B7: Libellé du risque | C7: G initial | D7: V initial | E7: Niveau initial | F7: G résiduel | G7: V résiduel | H7: Niveau résiduel
A8: R01 | B8: Compromission des résultats académiques par un étudiant | C8: G3 | D8: V3 | E8: Moyen (9) | F8: G3 | G8: V2 | H8: Moyen (6)
A9: R02 | B9: Paralysie de l'établissement par rançongiciel | C9: G4 | D9: V4 | E9: Élevé (16) | F9: G3 | G9: V2 | H9: Moyen (6)
A10: R03 | B10: Exfiltration et revente des données personnelles | C10: G4 | D10: V3 | E10: Élevé (12) | F10: G4 | G10: V2 | H10: Moyen (8)
A11: R04 | B11: Exfiltration du patrimoine scientifique par un acteur étatique | C11: G3 | D11: V2 | E11: Moyen (6) | F11: G3 | G11: V1 | H11: Faible (3)
A12: R05 | B12: Détournement de la paie par un personnel | C12: G3 | D12: V2 | E12: Moyen (6) | F12: G3 | G12: V1 | H12: Faible (3)
A13: R06 | B13: Destruction de données par vengeance | C13: G3 | D13: V2 | E13: Moyen (6) | F13: G2 | G13: V1 | H13: Faible (2)
A16: Cartographies visuelles (initial vs résiduel)

Sheet A5.2 Stratégie de traitement
A1: A5.2 - Stratégie de traitement du risque
A4: Pour chaque risque, la stratégie de traitement formalise la décision d'acceptation et l'objectif de réduction. Quatre options possibles selon le guide ANSSI : RÉDUIRE (mettre en place des mesures), TRANSFÉRER (vers un tiers : assurance, prestataire), ACCEPTER (sans action particulière), REFUSER (supprimer l'activité concernée). Pour UniCampus+, vu la nature des risques (impacts opérationnels et réputationnels critiques) et l'absence d'alternative au système d'information, la stratégie retenue est RÉDUIRE pour les 6 risques, avec des objectifs de réduction différenciés.
A6: Stratégie de traitement par risque
A7: Code | B7: Libellé du risque | C7: Niveau initial | D7: Stratégie retenue | E7: Niveau cible | F7: Justification et objectif de réduction
A8: R01 | B8: Compromission des résultats académiques par un étudiant | C8: Moyen (9) | D8: Réduire | E8: Moyen (6) | F8: Risque critique pour la réputation académique. Cible : ramener la vraisemblance à V2 par cloisonnement réseau, MFA enseignants et logs sur Moodle.
A9: R02 | B9: Paralysie de l'établissement par rançongiciel | C9: Élevé (16) | D9: Réduire | E9: Moyen (6) | F9: Risque le plus grave (G4 V4 = Élevé). Cible : réduire gravité à G3 grâce aux sauvegardes immuables et réduire vraisemblance à V2 par durcissement complet (suppression NOPASSWD, MFA, sensibilisation).
A10: R03 | B10: Exfiltration et revente des données personnelles | C10: Élevé (12) | D10: Réduire | E10: Moyen (8) | F10: Risque critique pour la conformité RGPD (G4 V3 = Élevé). Cible : maintenir gravité G4 (donnée exposée = perdue) mais réduire vraisemblance à V2 par chiffrement, hash bcrypt, WAF, et cloisonnement BDD.
A11: R04 | B11: Exfiltration du patrimoine scientifique par un acteur étatique | C11: Moyen (6) | D11: Réduire | E11: Faible (3) | F11: Risque sur le patrimoine scientifique. Cible : réduire vraisemblance à V1 par DLP, cloisonnement recherche, audit des partenaires (mesure A3.4).
A12: R05 | B12: Détournement de la paie par un personnel | C12: Moyen (6) | D12: Réduire | E12: Faible (3) | F12: Risque interne sur la chaîne RH. Cible : réduire vraisemblance à V1 par MFA, séparation des tâches, journalisation des modifications sensibles, révocation des comptes.
A13: R06 | B13: Destruction de données par vengeance | C13: Moyen (6) | D13: Réduire | E13: Faible (2) | F13: Risque interne. Cible : réduire à la fois gravité à G2 (réversibilité grâce aux sauvegardes immuables) et vraisemblance à V1 (révocation des comptes, journalisation immuable).

Sheet A5.3 Plan de traitement
A1: A5.3 - Plan de traitement du risque
A4: Plan de traitement complet des risques selon le format ANSSI p.77, structuré en 4 catégories : GOUVERNANCE, PROTECTION, DÉFENSE, RÉSILIENCE. Chaque mesure comporte : code, libellé, risques associés, responsable, freins de mise en œuvre, coût/complexité, charge estimée, échéance, priorité et statut. Certaines des mesures pourrons être implémenté dans la maquette V2 tandis que d'autres (notamment d'ordre gouvernance) ne peuvent pas.
A6: Plan de traitement du risque (26 mesures)
A7: Code | B7: Mesure de sécurité | C7: Risque(s) associé(s) | D7: Responsable | E7: Freins et difficultés | F7: Coût | G7: Charge estimée | H7: Échéance | I7: Priorité | J7: Statut
A8: GOUVERNANCE
A9: M01 | B9: Définition et publication d'une PSSI (Politique de Sécurité des Systèmes d'Information) incluant la politique de mots de passe (longueur minimale 12 caractères, complexité, rotation 12 mois) et la politique de gestion des comptes | C9: R02, R03, R05 | D9: RSSI / Direction | E9: Adoption par les utilisateurs, formation nécessaire | F9: + | G9: 10 j/h | H9: T0+3 mois | I9: P1 | J9: À lancer
A10: M02 | B10: Procédure formalisée de gestion du cycle de vie des comptes : création, modification, révocation automatique au départ du personnel, revue trimestrielle des comptes actifs | C10: R05, R06 | D10: DRH / DSI | E10: Coordination entre DRH et DSI nécessaire | F10: + | G10: 8 j/h | H10: T0+3 mois | I10: P1 | J10: À lancer
A11: M03 | B11: Charte d'usage du système d'information signée par chaque étudiant et personnel (à l'inscription et à la prise de poste), rappelant les obligations et sanctions | C11: R01, R05, R06 | D11: DRH / DSI | E11: Lourdeur administrative | F11: + | G11: 5 j/h | H11: T0+3 mois | I11: P2 | J11: À lancer
A12: M04 | B12: Élaboration et test du Plan de Continuité d'Activité (PCA) et du Plan de Reprise d'Activité (PRA) couvrant les services critiques (Moodle, RH, recherche) | C12: R02, R06 | D12: RSSI / Direction | E12: Coordination de toutes les directions, exercices coûteux | F12: ++ | G12: 30 j/h | H12: T0+12 mois | I12: P2 | J12: À lancer
A13: M05 | B13: Programme de sensibilisation cyber : campagne de phishing simulé trimestrielle, formations e-learning obligatoires, communications régulières | C13: R02, R03 | D13: RSSI | E13: Engagement des utilisateurs, budget annuel récurrent | F13: ++ | G13: Récurrente | H13: T0+3 mois puis continu | I13: P1 | J13: À lancer
A14: M06 | B14: Inclusion de clauses cyber dans les contrats des prestataires (RGPD, notification d'incident < 72 h, audit de sécurité périodique, droit d'audit) — cf. mesure A3.4 pour PR1 | C14: R02, R03, R04 | D14: RSSI / Direction Juridique | E14: Renégociation des contrats existants, résistance des prestataires | F14: + | G14: 15 j/h | H14: T0+6 mois | I14: P2 | J14: À lancer
A15: PROTECTION
A16: M07 | B16: Cloisonnement réseau : création de VLANs séparés pour étudiants (WiFi, salles info), personnel administratif, recherche, DSI/infrastructure, et DMZ publique — pare-feu entre les VLANs | C16: R01, R02, R03, R04 | D16: DSI | E16: Reconfiguration réseau lourde, interruptions de service | F16: ++ | G16: 20 j/h | H16: T0+6 mois | I16: P1 | J16: À lancer
A17: M08 | B17: Suppression du bind LDAP anonyme et activation de LDAPS (TLS) sur uc-srv-ldap ; ACLs strictes par compte et fonction | C17: R01, R03 | D17: DSI | E17: Mise à jour des applications clientes LDAP | F17: + | G17: 5 j/h | H17: T0+3 mois | I17: P1 | J17: À lancer
A18: M09 | B18: Migration des hashs SHA1 sans sel de uc-db-rh vers bcrypt (coût 12) ou argon2id ; renouvellement forcé des mots de passe des comptes affectés | C18: R02, R03, R05 | D18: DSI | E18: Renouvellement des mots de passe à orchestrer | F18: + | G18: 5 j/h | H18: T0+3 mois | I18: P1 | J18: À lancer
A19: M10 | B19: Suppression de sudo NOPASSWD sur uc-poste-dsi ; configuration sudo avec mot de passe, journalisation systématique via auditd | C19: R02, R06 | D19: DSI | E19: Adaptation des scripts d'administration | F19: + | G19: 3 j/h | H19: T0+3 mois | I19: P1 | J19: À lancer
A20: M11 | B20: Activation HTTPS/TLS systématique sur toutes les applications web (Moodle, RH, etc.) via Let's Encrypt ou PKI interne ; redirection HTTP → HTTPS | C20: R03, R05 | D20: DSI | E20: Gestion des certificats, mise à jour des liens internes | F20: + | G20: 8 j/h | H20: T0+3 mois | I20: P1 | J20: À lancer
A21: M12 | B21: Restriction de l'écoute de uc-db-rh sur 127.0.0.1 (binding local) ou réseau RH uniquement ; suppression de l'écoute 0.0.0.0:3306 | C21: R03, R05 | D21: DSI | E21: Aucun | F21: + | G21: 1 j/h | H21: T0+3 mois | I21: P1 | J21: À lancer
A22: M13 | B22: Remplacement du VPN PPTP legacy (MPPE-128 RC4 déprécié) par WireGuard ou OpenVPN avec authentification par certificats X.509 | C22: R02 | D22: DSI | E22: Distribution des certificats aux personnels distants | F22: + | G22: 10 j/h | H22: T0+6 mois | I22: P2 | J22: À lancer
A23: M14 | B23: Suppression du compte VPN partagé (campus / unicampus2024) ; création de comptes individuels avec rotation des credentials et révocation à la sortie | C23: R02, R06 | D23: DSI | E23: Création de comptes individuels en volume | F23: + | G23: 5 j/h | H23: T0+3 mois | I23: P1 | J23: À lancer
A24: M15 | B24: Mise en place d'une authentification multifacteur (MFA) sur les applications critiques : Moodle (enseignants/admins), uc-web-rh, accès VPN, comptes administrateurs | C24: R01, R02, R03, R05 | D24: DSI / RSSI | E24: Adoption utilisateurs, gestion des tokens | F24: ++ | G24: 15 j/h | H24: T0+6 mois | I24: P1 | J24: À lancer
A25: M16 | B25: Installation d'un WAF (Web Application Firewall) devant uc-web-moodle et uc-web-rh avec règles OWASP CRS, protection contre injections SQL, XSS, brute-force | C25: R03 | D25: DSI | E25: Ajustement des règles pour éviter les faux positifs | F25: ++ | G25: 10 j/h | H25: T0+9 mois | I25: P2 | J25: À lancer
A26: DÉFENSE
A27: M17 | B27: Mise en place d'un système de logs centralisés (rsyslog + Graylog ou ELK) collectant les journaux de tous les serveurs, applications, équipements réseau ; rétention 12 mois minimum, conservation immuable | C27: Tous | D27: DSI / RSSI | E27: Volume de logs important, stockage à provisionner | F27: ++ | G27: 20 j/h | H27: T0+6 mois | I27: P1 | J27: À lancer
A28: M18 | B28: Déploiement d'une sonde IDS/IPS (Suricata) en bordure DMZ et entre VLANs, avec règles Emerging Threats à jour | C28: R02, R03 | D28: DSI / RSSI | E28: Maintenance des règles, ajustements | F28: ++ | G28: 15 j/h | H28: T0+9 mois | I28: P2 | J28: À lancer
A29: M19 | B29: Mise en place d'un SIEM (Wazuh ou équivalent) pour la corrélation des événements, la détection d'anomalies et l'alerte temps réel ; définition de cas d'usage prioritaires | C29: Tous | D29: RSSI | E29: Compétences nécessaires pour configurer les règles | F29: +++ | G29: 30 j/h | H29: T0+12 mois | I29: P2 | J29: À lancer
A30: M20 | B30: Sonde DLP (Data Loss Prevention) sur les flux sortants pour détecter les exfiltrations de fichiers de recherche en volume | C30: R03, R04 | D30: RSSI | E30: Définition des règles DLP, faux positifs | F30: +++ | G30: 20 j/h | H30: T0+18 mois | I30: P3 | J30: À lancer
A31: M21 | B31: Déploiement d'un EDR (Endpoint Detection and Response) sur les postes de la DSI et du personnel administratif, extension progressive aux postes étudiants | C31: R02 | D31: DSI | E31: Licences EDR, impact performance | F31: +++ | G31: 20 j/h | H31: T0+12 mois | I31: P2 | J31: À lancer
A32: RÉSILIENCE
A33: M22 | B33: Mise en place de sauvegardes immuables : snapshots LVM read-only, externalisation vers stockage S3-compatible avec Object Lock, sauvegardes 3-2-1, rétention différentielle 30/90/365 jours | C33: R02, R06 | D33: DSI | E33: Stockage à provisionner, bande passante | F33: ++ | G33: 15 j/h | H33: T0+6 mois | I33: P1 | J33: À lancer
A34: M23 | B34: Tests de restauration semestriels documentés sur un échantillon représentatif (Moodle, RH, recherche) ; validation du RTO et du RPO contractuels | C34: R02, R06 | D34: DSI | E34: Mobilisation des équipes pour les tests | F34: + | G34: 10 j/h / semestre | H34: T0+9 mois puis continu | I34: P2 | J34: À lancer
A35: M24 | B35: Snapshots automatiques quotidiens des VMs critiques au niveau hyperviseur, rétention 7 jours en local, 30 jours hors-site | C35: R02, R06 | D35: DSI | E35: Stockage à provisionner | F35: + | G35: 5 j/h | H35: T0+3 mois | I35: P1 | J35: À lancer
A36: M25 | B36: Mise en haute disponibilité (HA) des services critiques : LDAP (réplication maître-maître), base de données (réplication ou cluster), serveurs DNS internes | C36: R02 | D36: DSI | E36: Complexité opérationnelle, double infrastructure | F36: +++ | G36: 30 j/h | H36: T0+18 mois | I36: P3 | J36: À lancer
A37: M26 | B37: Procédure de réponse à incident (PRI) formalisée et testée : équipe de réponse, playbooks par type d'incident (rançongiciel, intrusion, fuite de données), communication de crise | C37: Tous | D37: RSSI | E37: Exercices de gestion de crise à organiser | F37: ++ | G37: 20 j/h | H37: T0+9 mois | I37: P2 | J37: À lancer
A39: Statistiques du plan de traitement
A40: Nombre total de mesures : 26
A41: Mesures implémentées dans la maquette v2 (échéance T0+6 mois max) : 10
A42: Mesures prioritaires P1 : 14
A43: Répartition par catégorie : GOUVERNANCE : 6, PROTECTION : 10, DÉFENSE : 5, RÉSILIENCE : 5

Sheet A5.4 Risques résiduels
A1: A5.4 - Risques résiduels (fiches détaillées)
A4: Documentation des 6 risques résiduels RR01 à RR06 selon le modèle ANSSI p.78. Chaque fiche détaille : description du risque résiduel, vulnérabilités résiduelles persistantes après application des mesures, événements redoutés concernés, mesures de traitement appliquées, gravité/vraisemblance/niveau initial et résiduel, et modalités de suivi spécifique. Ces fiches constituent la base de la commission d'homologation et seront mises à jour selon le cycle de revue défini en A5.5.
A8: RR01 — Compromission des résultats académiques par un étudiant
A9: Description : | B9: Après application des mesures (cloisonnement réseau, MFA enseignants, logs centralisés, suppression du bind LDAP anonyme), la compromission directe des notes via énumération LDAP et phishing devient significativement plus difficile. Le risque résiduel persiste sous forme de tentatives de phishing ciblées d'enseignants et d'utilisation de credentials volés en cas de défaillance MFA.
A10: Vulnérabilités résiduelles : | B10: • Persistance possible de credentials volés en cas de phishing réussi malgré MFA • Risque d'ingénierie sociale sur les enseignants restant exposés • Erreurs humaines dans la gestion des sessions Moodle (sessions partagées)
A11: Événements redoutés concernés : | B11: ER03
A12: Mesures de traitement appliquées : | B12: M07 Cloisonnement VLANs ; M08 LDAP anonyme + LDAPS ; M15 MFA ; M17 Logs centralisés ; M05 Sensibilisation phishing
A13: Estimation : | B13: Indicateur | C13: Initial | D13: Résiduel | E13: Réduction
B14: Gravité | C14: G3 | D14: G3 | E14: Aucune réduction
B15: Vraisemblance | C15: V3 | D15: V2 | E15: −1
B16: Niveau de risque | C16: Moyen (9) | D16: Moyen (6) | E16: −3 (33 %)
A17: Suivi du risque résiduel : | B17: Indicateur : nombre de tentatives de phishing simulé détectées par les enseignants. Revue : trimestrielle.
A19: RR02 — Paralysie de l'établissement par rançongiciel
A20: Description : | B20: Risque résiduel principal après mise en œuvre du plan complet. Les mesures (sauvegardes immuables, suppression sudo NOPASSWD, MFA, IDS/IPS, sensibilisation phishing) réduisent considérablement la probabilité de succès complet et la gravité (sauvegardes garantissant la reprise). Le risque résiduel porte sur une attaque partiellement réussie causant des perturbations temporaires.
A21: Vulnérabilités résiduelles : | B21: • Risque d'attaque 0-day non couverte par les signatures IDS/IPS • Persistance possible d'attaques de phishing très ciblées (spear-phishing avancé) • Durée de restauration depuis sauvegardes : RTO non encore validé • Risque sur le périmètre étudiant non couvert par EDR
A22: Événements redoutés concernés : | B22: ER06, ER04
A23: Mesures de traitement appliquées : | B23: M07 Cloisonnement ; M10 Suppression NOPASSWD ; M15 MFA ; M17 Logs centralisés ; M18 IDS/IPS ; M19 SIEM ; M21 EDR ; M22 Sauvegardes immuables ; M23 Tests restauration ; M05 Sensibilisation ; M26 Procédure de réponse à incident
A24: Estimation : | B24: Indicateur | C24: Initial | D24: Résiduel | E24: Réduction
B25: Gravité | C25: G4 | D25: G3 | E25: −1
B26: Vraisemblance | C26: V4 | D26: V2 | E26: −2
B27: Niveau de risque | C27: Élevé (16) | D27: Moyen (6) | E27: −10 (62 %)
A28: Suivi du risque résiduel : | B28: Indicateur : RTO mesuré lors des tests de restauration semestriels (cible < 24h). Revue : semestrielle.
A30: RR03 — Exfiltration et revente des données personnelles
A31: Description : | B31: Après mise en œuvre des mesures (HTTPS, hashs bcrypt, WAF, restriction BDD, MFA, DLP), la vraisemblance d'une exfiltration massive diminue. Néanmoins, la gravité reste élevée (G4) car toute donnée exfiltrée même en faible volume reste compromise définitivement et expose UniCampus+ aux obligations RGPD (notification CNIL sous 72 h, sanctions financières).
A32: Vulnérabilités résiduelles : | B32: • Risque persistant d'exfiltration ciblée de petits volumes • Faux positifs DLP pouvant masquer de réelles exfiltrations • Risque sur les sauvegardes externalisées si compromises • Risque sur les exports légitimes (vers ministère, partenaires)
A33: Événements redoutés concernés : | B33: ER01
A34: Mesures de traitement appliquées : | B34: M07 Cloisonnement ; M09 Hashs bcrypt ; M11 HTTPS/TLS ; M12 Restriction BDD ; M15 MFA ; M16 WAF ; M17 Logs centralisés ; M20 DLP ; M01 PSSI
A35: Estimation : | B35: Indicateur | C35: Initial | D35: Résiduel | E35: Réduction
B36: Gravité | C36: G4 | D36: G4 | E36: Aucune réduction
B37: Vraisemblance | C37: V3 | D37: V2 | E37: −1
B38: Niveau de risque | C38: Élevé (12) | D38: Moyen (8) | E38: −4 (33 %)
A39: Suivi du risque résiduel : | B39: Indicateur : nombre d'alertes DLP et taux de faux positifs. Revue : trimestrielle. Coordination avec DPO.
A41: RR04 — Exfiltration du patrimoine scientifique par un acteur étatique
A42: Description : | B42: Le risque résiduel est faible après application des mesures (cloisonnement recherche, DLP, audit des partenaires, clauses cyber dans les contrats). Néanmoins, la nature APT de la source (ressources illimitées, persistance) implique une vigilance continue. Le risque résiduel se concentre sur les vecteurs par rebond (partenaires moins matures).
A43: Vulnérabilités résiduelles : | B43: • Maturité cyber hétérogène des partenaires malgré les audits • Risque persistant via doctorants en thèse partagée • Risque de canal légitime utilisé pour l'exfiltration (mail externe vers comptes personnels)
A44: Événements redoutés concernés : | B44: ER02
A45: Mesures de traitement appliquées : | B45: M07 Cloisonnement ; M17 Logs centralisés ; M19 SIEM ; M20 DLP ; M06 Clauses cyber prestataires ; Mesures A3.4 écosystème
A46: Estimation : | B46: Indicateur | C46: Initial | D46: Résiduel | E46: Réduction
B47: Gravité | C47: G3 | D47: G3 | E47: Aucune réduction
B48: Vraisemblance | C48: V2 | D48: V1 | E48: −1
B49: Niveau de risque | C49: Moyen (6) | D49: Faible (3) | E49: −3 (50 %)
A50: Suivi du risque résiduel : | B50: Indicateur : nombre d'incidents signalés par les partenaires, résultats des audits annuels. Revue : annuelle, coordination directeur recherche.
A52: RR05 — Détournement de la paie par un personnel
A53: Description : | B53: Après mise en œuvre des mesures (MFA, journalisation des modifications RH, séparation des tâches, validation à 4 yeux sur les RIB), le risque résiduel devient faible. Le risque persistant porte sur la collusion entre personnels et sur les contournements organisationnels.
A54: Vulnérabilités résiduelles : | B54: • Risque de collusion entre deux personnels ayant des droits différents • Risque social engineering du support DSI pour reset de mot de passe • Risque sur les comptes temporaires (CDD, stagiaires)
A55: Événements redoutés concernés : | B55: ER05
A56: Mesures de traitement appliquées : | B56: M02 Révocation comptes ; M09 Hashs bcrypt ; M11 HTTPS ; M12 Restriction BDD ; M15 MFA ; M17 Logs centralisés ; M01 PSSI
A57: Estimation : | B57: Indicateur | C57: Initial | D57: Résiduel | E57: Réduction
B58: Gravité | C58: G3 | D58: G3 | E58: Aucune réduction
B59: Vraisemblance | C59: V2 | D59: V1 | E59: −1
B60: Niveau de risque | C60: Moyen (6) | D60: Faible (3) | E60: −3 (50 %)
A61: Suivi du risque résiduel : | B61: Indicateur : revue trimestrielle des comptes RH actifs, audit annuel des modifications de RIB. Revue : trimestrielle.
A63: RR06 — Destruction de données par vengeance
A64: Description : | B64: Après mise en œuvre des mesures (sauvegardes immuables, révocation comptes, journalisation), la gravité passe à G2 grâce à la réversibilité (sauvegardes) et la vraisemblance à V1 (révocation stricte au départ + logs). Le risque résiduel est faible mais subsiste pour les actes commis pendant la période d'emploi actif avant détection.
A65: Vulnérabilités résiduelles : | B65: • Délai de détection entre l'acte et son investigation (durant emploi actif) • Risque sur les données non couvertes par les sauvegardes immuables • Risque persistant sur les comptes très privilégiés (admin DSI)
A66: Événements redoutés concernés : | B66: ER05, ER09
A67: Mesures de traitement appliquées : | B67: M02 Révocation comptes ; M10 Suppression NOPASSWD ; M14 Comptes individuels VPN ; M17 Logs centralisés (immuables) ; M22 Sauvegardes immuables ; M24 Snapshots automatiques
A68: Estimation : | B68: Indicateur | C68: Initial | D68: Résiduel | E68: Réduction
B69: Gravité | C69: G3 | D69: G2 | E69: −1
B70: Vraisemblance | C70: V2 | D70: V1 | E70: −1
B71: Niveau de risque | C71: Moyen (6) | D71: Faible (2) | E71: −4 (67 %)
A72: Suivi du risque résiduel : | B72: Indicateur : délai moyen de révocation après départ (cible < 24h), nombre d'alertes sur comptes admin. Revue : trimestrielle.

Sheet A5.5 Cadre de suivi
A1: A5.5 - Cadre de suivi et de surveillance des risques
A4: Définition du cadre de gouvernance pour le maintien en condition de sécurité (cf. guide ANSSI p.81-82). Ce cadre comprend les indicateurs de pilotage, l'organisation des comités de revue, et les mécanismes de surveillance qui permettent l'amélioration continue. Il vient compléter le plan de traitement A5.3 en garantissant son suivi dans le temps.
A6: Indicateurs de pilotage par catégorie
A7: Catégorie | B7: Indicateur | C7: Fréquence | D7: Cible et seuil d'alerte
A8: Gouvernance | B8: Taux de tenue des comités de pilotage prévus | C8: Mensuelle | D8: Cible : 100 %. Alerte : < 80 %.
A9: Gouvernance | B9: Pourcentage de mesures du plan en statut « Terminée » | C9: Mensuelle | D9: Cible : 100 % à T0+24 mois. Alerte : retard > 3 mois.
A10: Gouvernance | B10: Budget consommé vs alloué par mesure | C10: Trimestrielle | D10: Alerte : > 110 % du budget initial.
A11: Protection | B11: Taux de comptes administrateurs avec MFA actif | C11: Mensuelle | D11: Cible : 100 %. Alerte : < 95 %.
A12: Protection | B12: Taux de comptes utilisateurs avec MFA actif | C12: Trimestrielle | D12: Cible : 80 % à T0+12 mois. Alerte : < 50 %.
A13: Protection | B13: Pourcentage de hashs SHA1 résiduels dans uc-db-rh | C13: Mensuelle | D13: Cible : 0 %. Alerte : > 5 %.
A14: Protection | B14: Nombre de bind LDAP anonymes encore détectés | C14: Mensuelle | D14: Cible : 0. Alerte : > 0.
A15: Défense | B15: Nombre d'alertes SIEM / mois (volumétrie) | C15: Mensuelle | D15: Suivi de tendance. Alerte : variation > 50 %.
A16: Défense | B16: Temps moyen de détection d'un incident (MTTD) | C16: Trimestrielle | D16: Cible : < 4 heures pour incident critique.
A17: Défense | B17: Pourcentage de logs collectés par rapport au périmètre | C17: Mensuelle | D17: Cible : 100 %. Alerte : < 90 %.
A18: Défense | B18: Nombre de campagnes de phishing simulées et taux de clic | C18: Trimestrielle | D18: Cible : taux de clic < 5 %. Alerte : > 15 %.
... A21: Résilience | B21: Délai de révocation des comptes après départ | C21: Mensuelle | D21: Cible : < 24 h. Alerte : > 72 h.
A24: Organisation des comités et cycle de revue
A25: Instance | B25: Composition | C25: Fréquence | D25: Objet et livrables
A26: Comité de pilotage SSI (COPIL) | B26: Direction, RSSI, DSI, représentant Métiers | C26: Trimestrielle (T0+3, T0+6, T0+9 mois) puis semestrielle en croisière | D26: Pilotage stratégique du plan de traitement, validation des arbitrages, présentation de l'avancement à la Direction, validation des évolutions de risque.
A27: Comité opérationnel SSI | B27: RSSI, DSI, équipe sécurité opérationnelle | C27: Mensuelle | D27: Suivi opérationnel des mesures, des indicateurs, des incidents, des nouvelles vulnérabilités, des écarts au plan.
A28: Revue annuelle des risques | B28: Direction, RSSI, DSI, DPO, Direction Juridique, représentants Métiers | C28: Annuelle (cycle stratégique) | D28: Révision complète de l'analyse de risque : missions, scénarios, écosystème. Décision de mise à jour de l'étude EBIOS RM si nécessaire.
A29: Commission d'homologation | B29: Direction, RSSI, DSI, DPO, autorité d'homologation | C29: Tous les 3 ans ou en cas d'évolution majeure | D29: Décision formelle d'homologation du SI, validation de l'acceptabilité des risques résiduels.
A31: Déclencheurs de mise à jour de l'analyse de risque
A32: Catégorie | B32: Déclencheur | C32: Responsable veille | D32: Action déclenchée
A33: Menace cyber | B33: Apparition d'une CVE majeure (CVSS ≥ 9) sur un bien support | C33: DSI / RSSI | D33: Évaluation immédiate de l'exposition, application du correctif sous 7 jours, revue du plan.
A34: Menace cyber | B34: Nouvelle vague d'attaques sectorielles (rançongiciels sur l'ESR) | C34: RSSI / CERT-FR | D34: Réévaluation de la vraisemblance des SO concernés, sensibilisation renforcée.
A35: Réglementation | B35: Évolution RGPD, directive NIS 2, exigences ANSSI | C35: DPO / Juridique | D35: Mise à jour des mesures organisationnelles, revue de la PSSI.
A36: Architecture | B36: Évolution majeure de l'architecture (nouveau service, migration) | C36: DSI | D36: Mise à jour des biens supports A1.2, réévaluation des scénarios concernés.
A37: Écosystème | B37: Nouveau partenaire ou prestataire, changement de prestataire | C37: RSSI / Achats | D37: Mise à jour de la cartographie A3.2, audit cyber du nouvel acteur.
A38: Incident | B38: Incident de sécurité avéré (interne ou écosystème) | C38: RSSI | D38: Retour d'expérience, mise à jour des scénarios, ajustement des mesures.
A39: Cycle | B39: Échéance du cycle stratégique (1 an) | C39: RSSI | D39: Revue annuelle complète de l'analyse de risque.
